Metadata-Version: 2.1
Name: kodexam
Version: 0.0.1
Summary: Very useful thing
Home-page: 
Author: Dimasik
Author-email: drobyshevskiydk@gmail.com
License: MIT
Keywords: kod
Classifier: Development Status :: 5 - Production/Stable
Classifier: Intended Audience :: Education
Classifier: Operating System :: Microsoft :: Windows :: Windows 10
Classifier: License :: OSI Approved :: MIT License
Classifier: Programming Language :: Python :: 3
License-File: LICENSE.txt
